{
  "class-11-term0-english.pdf": {
    "Unit 1": {
      "Prose: The Portrait of a Lady": {
        "pdf_range": [7,25],
        "print_range": [1,19]
      },
      "Poem: Once Upon a Time": {
        "pdf_range": [26,32],
        "print_range": [20,26]
      },
      "Supplementary: After Twenty Years": {
        "pdf_range": [33,39],
        "print_range": [27,33]
      }
    },

    "Unit 2": {
      "Prose: The Queen of Boxing": {
        "pdf_range": [40,58],
        "print_range": [34,52]
      },
      "Poem: Confessions of a Born Spectator": {
        "pdf_range": [59,63],
        "print_range": [53,57]
      },
      "Supplementary: A Shot in the Dark": {
        "pdf_range": [64,71],
        "print_range": [58,65]
      }
    },

    "Unit 3": {
      "Prose: Forgetting": {
        "pdf_range": [72,90],
        "print_range": [66,84]
      },
      "Poem: Lines Written in the Early Spring": {
        "pdf_range": [91,95],
        "print_range": [85,89]
      },
      "Supplementary: The First Patient (Play)": {
        "pdf_range": [96,109],
        "print_range": [90,103]
      }
    },

    "Unit 4": {
      "Prose: Tight Corners": {
        "pdf_range": [110,131],
        "print_range": [104,125]
      },
      "Poem: Macavity - The Mystery Cat": {
        "pdf_range": [132,137],
        "print_range": [126,131]
      },
      "Supplementary: With the Photographer": {
        "pdf_range": [138,143],
        "print_range": [132,137]
      }
    },

    "Unit 5": {
      "Prose: The Convocation Address": {
        "pdf_range": [144,161],
        "print_range": [138,155]
      },
      "Poem: Everest is not the Only Peak": {
        "pdf_range": [162,165],
        "print_range": [156,159]
      },
      "Supplementary: The Singing Lesson": {
        "pdf_range": [166,173],
        "print_range": [160,167]
      }
    },

    "Unit 6": {
      "Prose: The Accidental Tourist": {
        "pdf_range": [174,188],
        "print_range": [168,182]
      },
      "Poem: The Hollow Crown": {
        "pdf_range": [189,195],
        "print_range": [183,189]
      },
      "Supplementary: The Never Never Nest (Play)": {
        "pdf_range": [196,209],
        "print_range": [190,203]
      }
    }
  }
}
